pyspbla/__init__.py
pyspbla/__main__.py
pyspbla/bridge.py
pyspbla/gviz.py
pyspbla/io.py
pyspbla/libspbla.so
pyspbla/matrix.py
pyspbla/utils.py
pyspbla/wrapper.py
pyspbla-1.0.1.dist-info/LICENSE
pyspbla-1.0.1.dist-info/METADATA
pyspbla-1.0.1.dist-info/WHEEL
pyspbla-1.0.1.dist-info/top_level.txt
pyspbla-1.0.1.dist-info/RECORD
