Metadata-Version: 2.1
Name: pyspbla
Version: 1.0.1
Summary: spbla library python bindings.
Home-page: https://github.com/JetBrains-Research/spbla
Author: Egor Orachyov
Author-email: egororachyov@gmail.com
License: MIT
Project-URL: spbla project, https://github.com/JetBrains-Research/spbla
Project-URL: Bug Tracker, https://github.com/JetBrains-Research/spbla/issues
Keywords: python,cplusplus,sparse-matrix,linear-algebra,graph-analysis,graph-algorithms,graphblas,nvidia-cuda,opencl
Platform: UNKNOWN
Classifier: Development Status :: 5 - Production/Stable
Classifier: Programming Language :: Python :: 3
Classifier: Programming Language :: C++
Classifier: License :: OSI Approved :: MIT License
Classifier: Operating System :: POSIX :: Linux
Classifier: Environment :: GPU
Classifier: Environment :: GPU :: NVIDIA CUDA
Classifier: Environment :: Console
Classifier: Intended Audience :: Developers
Classifier: Intended Audience :: End Users/Desktop
Classifier: Intended Audience :: Information Technology
Classifier: Intended Audience :: Science/Research
Classifier: Natural Language :: English
Classifier: Topic :: Scientific/Engineering :: Information Analysis
Requires-Python: >=3.0
